{
	"configurations" : 
	[
		{
			"directories" : 
			[
				{
					"build" : ".",
					"jsonFile" : "directory-.-Debug-f5ebdc15457944623624.json",
					"minimumCMakeVersion" : 
					{
						"string" : "3.26"
					},
					"projectIndex" : 0,
					"source" : ".",
					"targetIndexes" : 
					[
						0,
						1
					]
				}
			],
			"name" : "Debug",
			"projects" : 
			[
				{
					"directoryIndexes" : 
					[
						0
					],
					"name" : "cppexe",
					"targetIndexes" : 
					[
						0,
						1
					]
				}
			],
			"targets" : 
			[
				{
					"directoryIndex" : 0,
					"id" : "Time::@6890427a1f51a3e7e1df",
					"jsonFile" : "target-Time-Debug-1bf9bae1aecac8c93540.json",
					"name" : "Time",
					"projectIndex" : 0
				},
				{
					"directoryIndex" : 0,
					"id" : "cppexe::@6890427a1f51a3e7e1df",
					"jsonFile" : "target-cppexe-Debug-103af24db28822fd0ffc.json",
					"name" : "cppexe",
					"projectIndex" : 0
				}
			]
		}
	],
	"kind" : "codemodel",
	"paths" : 
	{
		"build" : "/Users/loujilin/CLionProjects/cppexe/cmake-build-debug",
		"source" : "/Users/loujilin/CLionProjects/cppexe"
	},
	"version" : 
	{
		"major" : 2,
		"minor" : 5
	}
}
